[
  {
    "descripcion": "Chocolatina Jet Mani Jumbo",
    "vencimiento": "2024-12-12",
    "tipo": "GOLOSINAS",
    "iva": 19,
    "valorVenta": 4000,
    "subtotal": 141000,
    "id": "PVEPR",
    "valorBase": 3000,
    "disponible": 47
  },
  {
    "descripcion": "Boliqueso",
    "vencimiento": "2024-12-10",
    "tipo": "GOLOSINAS",
    "iva": 19,
    "valorVenta": 1100,
    "subtotal": 29000,
    "id": "LCB2M",
    "valorBase": 1000,
    "disponible": 29
  },
  {
    "descripcion": "Queso parmesano Alpina",
    "vencimiento": "2024-10-01",
    "tipo": "LACTEOS",
    "iva": 19,
    "valorVenta": 12000,
    "subtotal": 480000,
    "id": "CU12G",
    "valorBase": 10000,
    "disponible": 48
  },
  {
    "descripcion": "Yogurt natural vaso x 120 ml.",
    "vencimiento": "2024-08-01",
    "tipo": "LACTEOS",
    "iva": 19,
    "valorVenta": 5000,
    "subtotal": 40000,
    "id": "35G6E",
    "valorBase": 4000,
    "disponible": 10
  },
  {
    "descripcion": "Yogurt piña vaso x 120 c.c.",
    "vencimiento": "2024-03-26",
    "tipo": "LACTEOS",
    "iva": 19,
    "valorVenta": 5000,
    "subtotal": 56000,
    "id": "X1SC9",
    "valorBase": 4000,
    "disponible": 14
  },
  {
    "descripcion": "Arroz Diana x libra",
    "vencimiento": "2024-03-26",
    "tipo": "CEREALES",
    "iva": 19,
    "valorVenta": 3999,
    "subtotal": 38987,
    "id": "6NTFM",
    "valorBase": 2999,
    "disponible": 13
  }
]